setup.py
smaplib/__init__.py
smaplib/fsio/__init__.py
smaplib/fsio/array.py
smaplib/fsio/common.py
smaplib/fsio/dss.py
smaplib/fsio/json.py
smaplib/fsio/pickle.py
smaplib/fsio/text.py
smaplib/img/__init__.py
smaplib/img/classes.py
smaplib/img/dss.py
smaplib/img/helpers.py
smaplib/img/plot.py
smaplib/misc/__init__.py
smaplib/misc/common.py
smaplib/misc/http.py
smaplib/misc/iterable.py
smaplib/misc/tests/__init__.py
smaplib/misc/tests/test_common.py
smaplib/pnc/__init__.py
smaplib/pnc/classes.py
smaplib/pnc/helpers.py
smaplib/sim/__init__.py
smaplib/sim/dataset.py
smaplib/sim/feature.py
smaplib/sim/layer.py
smaplib/sim/model.py
smaplib/sim/pca.py
smaplib/sim/trainer.py
smaplib/similarity/__init__.py
smaplib/similarity/feature.py
smaplib/similarity/manager.py
smaplib/tsfl/__init__.py
smaplib/tsfl/helpers.py
smaplib-1.0.3.dist-info/LICENSE
smaplib-1.0.3.dist-info/METADATA
smaplib-1.0.3.dist-info/WHEEL
smaplib-1.0.3.dist-info/top_level.txt
smaplib-1.0.3.dist-info/RECORD
