Metadata-Version: 2.1
Name: smaplib
Version: 1.0.3
Summary: The `smaplib` package provides some useful similarity mapping related modeling functions
Home-page: https://github.com/braibaud/smaplib
Author: Benjamin Raibaud
Author-email: braibaud@gmail.com
Maintainer: Benjamin Raibaud
Maintainer-email: braibaud@gmail.com
License: MIT
Classifier: Development Status :: 4 - Beta
Classifier: Intended Audience :: Developers
Classifier: Intended Audience :: Education
Classifier: Intended Audience :: Science/Research
Classifier: License :: OSI Approved :: MIT License
Classifier: Programming Language :: Python :: 3.9
Classifier: Topic :: Software Development :: Libraries
Classifier: Topic :: Software Development :: Libraries :: Python Modules
Classifier: Topic :: Scientific/Engineering :: Artificial Intelligence
Requires-Python: >=3.9
License-File: LICENSE
Requires-Dist: pinecone-client (>=2.0)
Requires-Dist: tensorflow-hub (>=0.12)
Requires-Dist: tensorflow (>=2.5)
Requires-Dist: matplotlib (>=3.0)
Requires-Dist: pillow (>=9.0)
Requires-Dist: pandas (>=1.4)
Requires-Dist: tqdm (>=4.0)
Requires-Dist: dataiku-api-client (>=11.0)
Requires-Dist: scikit-learn (>=1.2)
